m_you/__init__.py
m_you/button.py
m_you/checkbox.py
m_you/dropdown.py
m_you/input.py
m_you/radiobutton.py
m_you/slider.py
m_you/switch.py
m_you/toast.py
m_you/assets/material.ttf
m_you_tk-0.1.1.dist-info/licenses/LICENSE
m_you_tk-0.1.1.dist-info/METADATA
m_you_tk-0.1.1.dist-info/WHEEL
m_you_tk-0.1.1.dist-info/top_level.txt
m_you_tk-0.1.1.dist-info/RECORD
