Metadata-Version: 2.4
Name: m-you-tk
Version: 0.1.1
Summary: Material You components for Tkinter
Author-email: logic-break <abibasqabiba@email.com>
Requires-Python: >=3.7
License-File: LICENSE
Requires-Dist: Pillow>=9.0.0
Dynamic: license-file
